Metadata-Version: 2.4
Name: osm-osw-reformatter
Version: 0.3.1
Summary: Python package to convert OSM to OSW and OSW to OSM
Home-page: https://github.com/TaskarCenterAtUW/TDEI-python-lib-osw-formatter
Author: Sujata Misra
Author-email: sujatam@gaussiansolutions.com
Project-URL: Documentation, https://github.com/TaskarCenterAtUW/TDEI-python-lib-osw-formatter/blob/main/README.md
Project-URL: GitHub, https://github.com/TaskarCenterAtUW/TDEI-python-lib-osw-formatter
Project-URL: Changelog, https://github.com/TaskarCenterAtUW/TDEI-python-lib-osw-formatter/blob/develop/CHANGELOG.md
Classifier: Programming Language :: Python :: 3
Classifier: License :: OSI Approved :: MIT License
Classifier: Operating System :: OS Independent
Requires-Python: >=3.10
License-File: LICENSE
Requires-Dist: osmium~=3.6.0
Requires-Dist: asyncio~=3.4.3
Requires-Dist: networkx~=3.2
Requires-Dist: shapely~=2.0.2
Requires-Dist: pyproj~=3.6.1
Requires-Dist: coverage~=7.5.1
Requires-Dist: ogr2osm==1.2.0
Requires-Dist: python-osw-validation==0.3.1
Dynamic: author
Dynamic: author-email
Dynamic: classifier
Dynamic: description
Dynamic: description-content-type
Dynamic: home-page
Dynamic: license-file
Dynamic: project-url
Dynamic: requires-dist
Dynamic: requires-python
Dynamic: summary
